verilog-main/drive-download-20260602T032443Z-3-001/EX1/design.v
module shift_reg_blocking (
    input clk,
    input D,
    output reg [3:0] Q1
);
    integer i;
    always @(posedge clk) begin
        for (i = 0; i < 3; i = i + 1) begin
            if (i == 0)
                Q1[0] = D;
            Q1[i+1] = Q1[i];
        end
    end
endmodule

verilog-main/drive-download-20260602T032443Z-3-001/EX1/testbench.v
`timescale 1ns / 1ps

module shift_reg_blocking_tb;
    reg clk;
    reg D;
    wire [3:0] Q1;

    
    shift_reg_blocking u_Q1 (
        .clk(clk),
        .D(D),
        .Q1(Q1)
    );

    
    always #55 clk = ~clk;

    initial 
    begin
        clk = 0;
        D = 0;
        
        
        $dumpfile("shift_reg_blocking.vcd");
        $dumpvars(0, shift_reg_blocking_tb);

        
        #110 D = 1;
        #110 D = 0;
        #110 D = 1;
        #110 D = 0;
        #110 D = 1;
        #110 D = 0;
        #110 D = 1;
        #110 D = 0;
        #110 D = 1;
        #110 D = 1;
        #110 D = 0;
        #110 D = 1;
        #110 D = 0;
        #110 D = 0;
        #110 D = 1;
        #110 D = 0;
        #110 D = 0;
        #110 D = 1;
        #110 D = 1;
        
        #110;
        $finish; 
    end
endmodule

verilog-main/drive-download-20260602T032443Z-3-001/EX1/shift_reg_blocking.vcd
$date
	Tue May 19 11:24:36 2026
$end
$version
	Icarus Verilog
$end
$timescale
	1ps
$end
$scope module shift_reg_blocking_tb $end
$var wire 4 ! Q1 [3:0] $end
$var reg 1 " D $end
$var reg 1 # clk $end
$scope module u_Q1 $end
$var wire 1 " D $end
$var wire 1 # clk $end
$var reg 4 $ Q1 [3:0] $end
$var integer 32 % i [31:0] $end
$upscope $end
$upscope $end
$enddefinitions $end
$comment Show the parameter values. $end
$dumpall
$end
#0
$dumpvars
bx %
bx $
0#
0"
bx !
$end
#55000
b0 !
b0 $
b11 %
1#
#110000
0#
1"
#165000
b1111 !
b1111 $
b11 %
1#
#220000
0#
0"
#275000
b0 !
b0 $
b11 %
1#
#330000
0#
1"
#385000
b1111 !
b1111 $
b11 %
1#
#440000
0#
0"
#495000
b0 !
b0 $
b11 %
1#
#550000
0#
1"
#605000
b1111 !
b1111 $
b11 %
1#
#660000
0#
0"
#715000
b0 !
b0 $
b11 %
1#
#770000
0#
1"
#825000
b1111 !
b1111 $
b11 %
1#
#880000
0#
0"
#935000
b0 !
b0 $
b11 %
1#
#990000
0#
1"
#1045000
b1111 !
b1111 $
b11 %
1#
#1100000
0#
#1155000
b11 %
1#
#1210000
0#
0"
#1265000
b0 !
b0 $
b11 %
1#
#1320000
0#
1"
#1375000
b1111 !
b1111 $
b11 %
1#
#1430000
0#
0"
#1485000
b0 !
b0 $
b11 %
1#
#1540000
0#
#1595000
b11 %
1#
#1650000
0#
1"
#1705000
b1111 !
b1111 $
b11 %
1#
#1760000
0#
0"
#1815000
b0 !
b0 $
b11 %
1#
#1870000
0#
#1925000
b11 %
1#
#1980000
0#
1"
#2035000
b1111 !
b1111 $
b11 %
1#
#2090000
0#
#2145000
b11 %
1#
