verilog-main/drive-download-20260602T032501Z-3-001/EX1/design.v
module L1 (A,B,Ci,Co,S);
    input A,B,Ci ;
    output Co,S ;
    and (AB,A,B);
    and (ACi,A,Ci);
    and (BCi,B,Ci);
    xor (S,A,B,Ci);
endmodule

verilog-main/drive-download-20260602T032501Z-3-001/EX1/testbench.v
`timescale 1ns/1ns

module L1_testbench;
    reg A,B,Ci;
    wire Co,S;

    L1 uut (
        .A(A),
        .B(B),
        .Ci(Ci),
        .Co(Co),
        .S(S)
    );

    initial begin
        A = 1'B0 ;
        B = 1'B0 ;
        Ci = 1'B0 ;
        #100 ;
        A = 1'B0 ;
        B = 1'B0 ;
        Ci = 1'B1 ;
        #100 ;
        A = 1'B0 ;
        B = 1'B1 ;
        Ci = 1'B0 ;
        #100 ;
        A = 1'B0 ;
        B = 1'B1 ;
        Ci = 1'B1 ;
        #100 ;
        A = 1'B1 ;
        B = 1'B0 ;
        Ci = 1'B0 ;
        #100 ;
        A = 1'B1 ;
        B = 1'B0 ;
        Ci = 1'B1 ;
        #100 ;
        A = 1'B1 ;
        B = 1'B1 ;
        Ci = 1'B0 ;
        #100 ;
        A = 1'B1 ;
        B = 1'B1 ;
        Ci = 1'B1 ;
    end

    initial begin
        $display("開始測試...");
        #1000
        $finish();
    end

    initial begin
        $dumpfile("L1TB.vcd");
        $dumpvars(0);
    end
    
endmodule

verilog-main/drive-download-20260602T032501Z-3-001/EX1/L1TB.vcd
$date
	Tue May 05 17:21:12 2026
$end
$version
	Icarus Verilog
$end
$timescale
	1ns
$end
$scope module L1_testbench $end
$var wire 1 ! Co $end
$var wire 1 " S $end
$var reg 1 # A $end
$var reg 1 $ B $end
$var reg 1 % Ci $end
$scope module uut $end
$var wire 1 # A $end
$var wire 1 & AB $end
$var wire 1 ' ACi $end
$var wire 1 $ B $end
$var wire 1 ( BCi $end
$var wire 1 % Ci $end
$var wire 1 ! Co $end
$var wire 1 " S $end
$upscope $end
$upscope $end
$enddefinitions $end
$comment Show the parameter values. $end
$dumpall
$end
#0
$dumpvars
0(
0'
0&
0%
0$
0#
0"
z!
$end
#100
1"
1%
#200
0%
1$
#300
1(
0"
1%
#400
0(
1"
0%
0$
1#
#500
1'
0"
1%
#600
0'
1&
0%
1$
#700
1'
1(
1"
1%
