20260526_Ex2/design.sv
module fulladd(A, B, Ci, S, Co);
  input A, B, Ci;
  output S, Co;

  wire AB, ACi, BCi, xorAB;

  and(AB, A, B);
  and(ACi, A, Ci);
  and(BCi, B, Ci);
  or(Co, AB, ACi, BCi);

  xor(xorAB, A, B);
  xor(S, xorAB, Ci);
endmodule

20260526_Ex1/testbench.sv
`timescale 1ns/1ns
module fulladd_test();
  // constants
  
  // general purpose registers
  reg A,B, Ci;
   
  // wires
  wire SOut;
  wire CoOut;


  fulladd uut(
    .A(A),
    .B(B),
    .Ci(Ci),
    .Co(CoOut),
    .S(SOut)
  );

  initial    
  begin
    A=1'b0; //A=0
    B=1'b0; //B=0
	Ci=1'b0; //Ci=0
    #20;
    A=1'b0;
    B=1'b0;
	Ci=1'b1;
    #20;
    A=1'b0;
    B=1'b1; 
	Ci=1'b0;
    #20;
    A=1'b0; 
    B=1'b1;
	Ci=1'b1;
    #20;
    A=1'b1;
    B=1'b0;
	Ci=1'b0;
    #20;
    A=1'b1; 
    B=1'b0; 
	Ci=1'b1;
    #20;
    A=1'b1; 
    B=1'b1;
	Ci=1'b0;
    #20;
    A=1'b1;
    B=1'b1;
    Ci=1'b1;
    #20;
  end 
      
  initial 
  begin
    $display("Starting Testbench...");
    #180;
    $finish();
  end

  initial 
  begin
    $dumpfile("dump.vcd");
    $dumpvars(0);
  end
endmodule

20260505_Ex1/dump.vcd
$date
	Tue Jun  2 09:50:55 2026
$end
$version
	Icarus Verilog
$end
$timescale
	1ns
$end
$scope module fulladd_test $end
$var wire 1 ! SOut $end
$var wire 1 " CoOut $end
$var reg 1 # A $end
$var reg 1 $ B $end
$var reg 1 % Ci $end
$scope module uut $end
$var wire 1 # A $end
$var wire 1 & AB $end
$var wire 1 ' ACi $end
$var wire 1 $ B $end
$var wire 1 ( BCi $end
$var wire 1 % Ci $end
$var wire 1 " Co $end
$var wire 1 ! S $end
$var wire 1 ) xorAB $end
$upscope $end
$upscope $end
$enddefinitions $end
$comment Show the parameter values. $end
$dumpall
$end
#0
$dumpvars
0)
0(
0'
0&
0%
0$
0#
0"
0!
$end
#20
1!
1%
#40
1)
0%
1$
#60
1"
1(
0!
1%
#80
0"
1!
0(
0%
0$
1#
#100
1"
1'
0!
1%
#120
0'
1&
0)
0%
1$
#140
1'
1(
1!
1%
