20260602_Ex2/design.sv
module Add3Assign(I2, I1, I0, O);
    input I2, I1, I0;
    output [2:0] O;

    assign O = {I2, I1, I0} + 3'b011;
endmodule

module Add3Gate(I2, I1, I0, O);
    input I2, I1, I0;
    output [2:0] O;
    wire nI2, nI1, nI0;
    wire o1_a, o1_b;
    wire o2_a, o2_b, o2_c;

    not(nI2, I2);
    not(nI1, I1);
    not(nI0, I0);

    not(O[0], I0);

    and(o1_a, nI1, nI0);
    and(o1_b, I1, I0);
    or(O[1], o1_a, o1_b);

    and(o2_a, I2, nI1, nI0);
    and(o2_b, nI2, I1);
    and(o2_c, nI2, I0);
    or(O[2], o2_a, o2_b, o2_c);
endmodule

module Add3If(I2, I1, I0, O);
    input I2, I1, I0;
    output reg [2:0] O;

    always @(*) begin
        if ({I2, I1, I0} == 3'b000) O = 3'b011;
        else if ({I2, I1, I0} == 3'b001) O = 3'b100;
        else if ({I2, I1, I0} == 3'b010) O = 3'b101;
        else if ({I2, I1, I0} == 3'b011) O = 3'b110;
        else if ({I2, I1, I0} == 3'b100) O = 3'b111;
        else if ({I2, I1, I0} == 3'b101) O = 3'b000;
        else if ({I2, I1, I0} == 3'b110) O = 3'b001;
        else O = 3'b010;
    end
endmodule

module Add3Case(I2, I1, I0, O);
    input I2, I1, I0;
    output reg [2:0] O;

    always @(*) begin
        case ({I2, I1, I0})
            3'b000: O = 3'b011;
            3'b001: O = 3'b100;
            3'b010: O = 3'b101;
            3'b011: O = 3'b110;
            3'b100: O = 3'b111;
            3'b101: O = 3'b000;
            3'b110: O = 3'b001;
            3'b111: O = 3'b010;
            default: O = 3'b000;
        endcase
    end
endmodule

20260602_Ex2/testbench.sv
`timescale 1ns/1ns

module Practice();
    reg I2, I1, I0;

    wire [2:0] add3_assign;
    wire [2:0] add3_gate;
    wire [2:0] add3_if;
    wire [2:0] add3_case;

    Add3Assign add3_a(.I2(I2), .I1(I1), .I0(I0), .O(add3_assign));
    Add3Gate add3_g(.I2(I2), .I1(I1), .I0(I0), .O(add3_gate));
    Add3If add3_i(.I2(I2), .I1(I1), .I0(I0), .O(add3_if));
    Add3Case add3_c(.I2(I2), .I1(I1), .I0(I0), .O(add3_case));

    initial begin
        $monitor("Time=%0d | I2I1I0=%b%b%b | add3=%b/%b/%b/%b",
                 $time, I2, I1, I0, add3_assign, add3_gate, add3_if, add3_case);

        I2 = 1'b0; I1 = 1'b0; I0 = 1'b0;
        #100;
        I2 = 1'b0; I1 = 1'b0; I0 = 1'b1;
        #100;
        I2 = 1'b0; I1 = 1'b1; I0 = 1'b0;
        #100;
        I2 = 1'b0; I1 = 1'b1; I0 = 1'b1;
        #100;
        I2 = 1'b1; I1 = 1'b0; I0 = 1'b0;
        #100;
        I2 = 1'b1; I1 = 1'b0; I0 = 1'b1;
        #100;
        I2 = 1'b1; I1 = 1'b1; I0 = 1'b0;
        #100;
        I2 = 1'b1; I1 = 1'b1; I0 = 1'b1;
        #100;
    end

    initial begin
        $display("Starting Testbench");
        #850;
        $finish;
    end

    initial begin
        $dumpfile("dump.vcd");
        $dumpvars(0);
    end
endmodule

20260602_Ex2/dump.vcd
$date
	Tue Jun  2 10:27:50 2026
$end
$version
	Icarus Verilog
$end
$timescale
	1ns
$end
$scope module Practice $end
$var wire 3 ! add3_if [2:0] $end
$var wire 3 " add3_gate [2:0] $end
$var wire 3 # add3_case [2:0] $end
$var wire 3 $ add3_assign [2:0] $end
$var reg 1 % I0 $end
$var reg 1 & I1 $end
$var reg 1 ' I2 $end
$scope module add3_a $end
$var wire 1 % I0 $end
$var wire 1 & I1 $end
$var wire 1 ' I2 $end
$var wire 3 ( O [2:0] $end
$upscope $end
$scope module add3_c $end
$var wire 1 % I0 $end
$var wire 1 & I1 $end
$var wire 1 ' I2 $end
$var reg 3 ) O [2:0] $end
$upscope $end
$scope module add3_g $end
$var wire 1 % I0 $end
$var wire 1 & I1 $end
$var wire 1 ' I2 $end
$var wire 1 * nI0 $end
$var wire 1 + nI1 $end
$var wire 1 , nI2 $end
$var wire 1 - o1_a $end
$var wire 1 . o1_b $end
$var wire 1 / o2_a $end
$var wire 1 0 o2_b $end
$var wire 1 1 o2_c $end
$var wire 3 2 O [2:0] $end
$upscope $end
$scope module add3_i $end
$var wire 1 % I0 $end
$var wire 1 & I1 $end
$var wire 1 ' I2 $end
$var reg 3 3 O [2:0] $end
$upscope $end
$upscope $end
$enddefinitions $end
$comment Show the parameter values. $end
$dumpall
$end
#0
$dumpvars
b11 3
b11 2
01
00
0/
0.
1-
1,
1+
1*
b11 )
b11 (
0'
0&
0%
b11 $
b11 #
b11 "
b11 !
$end
#100
0-
b100 "
b100 2
b100 $
b100 (
b100 !
b100 3
b100 #
b100 )
0*
11
1%
#200
b101 "
b101 2
1*
01
b101 $
b101 (
b101 #
b101 )
b101 !
b101 3
0+
10
0%
1&
#300
b110 "
b110 2
b110 $
b110 (
b110 !
b110 3
b110 #
b110 )
0*
1.
11
1%
#400
b111 "
b111 2
1-
1/
1*
01
1+
0.
00
b111 $
b111 (
b111 #
b111 )
b111 !
b111 3
0,
0%
0&
1'
#500
0-
0/
b0 "
b0 2
b0 $
b0 (
b0 !
b0 3
b0 #
b0 )
0*
1%
#600
b1 "
b1 2
1*
b1 $
b1 (
b1 #
b1 )
b1 !
b1 3
0+
0%
1&
#700
b10 "
b10 2
b10 $
b10 (
b10 !
b10 3
b10 #
b10 )
0*
1.
1%
