verilog-main/drive-download-20260602T032436Z-3-001/EX2/design.v
module Excess_3_Dataflow (
    input I2, I1, I0,
    output O2, O1, O0
);
    assign O0 = ~I0;
    assign O1 = ~(I1 ^ I0);
    assign O2 = (~I2 & (I1 | I0)) | (I2 & ~I1 & ~I0);

endmodule

module Excess_3_If (
    input I2, I1, I0,
    output reg O2, O1, O0
);
    always @(*) begin
        if ({I2, I1, I0} == 3'b000)      {O2, O1, O0} = 3'b011;
        else if ({I2, I1, I0} == 3'b001) {O2, O1, O0} = 3'b100;
        else if ({I2, I1, I0} == 3'b010) {O2, O1, O0} = 3'b101;
        else if ({I2, I1, I0} == 3'b011) {O2, O1, O0} = 3'b110;
        else if ({I2, I1, I0} == 3'b100) {O2, O1, O0} = 3'b111;
        else if ({I2, I1, I0} == 3'b101) {O2, O1, O0} = 3'b000;
        else if ({I2, I1, I0} == 3'b110) {O2, O1, O0} = 3'b001;
        else                             {O2, O1, O0} = 3'b010;
    end
endmodule

verilog-main/drive-download-20260602T032436Z-3-001/EX2/testbench.v
`timescale 1ns/1ns

module Excess_3_tb;
    reg t_I2, t_I1, t_I0;
    wire t_O2_df, t_O1_df, t_O0_df;
    wire t_O2_if, t_O1_if, t_O0_if;

    Excess_3_Dataflow uut1 (
        .I2(t_I2),
        .I1(t_I1), 
        .I0(t_I0),  
        .O2(t_O2_df), 
        .O1(t_O1_df), 
        .O0(t_O0_df)
    );

    Excess_3_If uut2 (
        .I2(t_I2),
        .I1(t_I1), 
        .I0(t_I0),  
        .O2(t_O2_if), 
        .O1(t_O1_if), 
        .O0(t_O0_if)
    );

    initial begin
        $dumpfile("Excess_3.vcd");
        $dumpvars(0, Excess_3_tb); 
        

        t_I2 = 0; t_I1 = 0; t_I0 = 0; #10;
        t_I2 = 0; t_I1 = 0; t_I0 = 1; #10;
        t_I2 = 0; t_I1 = 1; t_I0 = 0; #10;
        t_I2 = 0; t_I1 = 1; t_I0 = 1; #10;
        t_I2 = 1; t_I1 = 0; t_I0 = 0; #10;
        t_I2 = 1; t_I1 = 0; t_I0 = 1; #10;
        t_I2 = 1; t_I1 = 1; t_I0 = 0; #10;
        t_I2 = 1; t_I1 = 1; t_I0 = 1; #10;
        
        $finish; 
    end
endmodule

verilog-main/drive-download-20260602T032436Z-3-001/EX2/Excess_3.vcd
$date
	Thu May 28 15:15:29 2026
$end
$version
	Icarus Verilog
$end
$timescale
	1ns
$end
$scope module Excess_3_tb $end
$var wire 1 ! t_O2_if $end
$var wire 1 " t_O2_df $end
$var wire 1 # t_O1_if $end
$var wire 1 $ t_O1_df $end
$var wire 1 % t_O0_if $end
$var wire 1 & t_O0_df $end
$var reg 1 ' t_I0 $end
$var reg 1 ( t_I1 $end
$var reg 1 ) t_I2 $end
$scope module uut1 $end
$var wire 1 ' I0 $end
$var wire 1 ( I1 $end
$var wire 1 ) I2 $end
$var wire 1 & O0 $end
$var wire 1 $ O1 $end
$var wire 1 " O2 $end
$upscope $end
$scope module uut2 $end
$var wire 1 ' I0 $end
$var wire 1 ( I1 $end
$var wire 1 ) I2 $end
$var reg 1 % O0 $end
$var reg 1 # O1 $end
$var reg 1 ! O2 $end
$upscope $end
$upscope $end
$enddefinitions $end
$comment Show the parameter values. $end
$dumpall
$end
#0
$dumpvars
0)
0(
0'
1&
1%
1$
1#
0"
0!
$end
#10
1"
0$
0&
1!
0#
0%
1'
#20
1&
1%
0'
1(
#30
1$
0&
1#
0%
1'
#40
1&
1%
0'
0(
1)
#50
0"
0$
0&
0!
0#
0%
1'
#60
1&
1%
0'
1(
#70
1$
0&
1#
0%
1'
