verilog-main/drive-download-20260602T032443Z-3-001/EX2/design.v
module shift_reg_nonblocking (
    input clk,
    input D,
    output reg [3:0] Q2
);
    integer i;
    always @(posedge clk) begin
        for (i = 0; i < 3; i = i + 1) begin
            if (i == 0)
                Q2[0] <= D;
            Q2[i+1] <= Q2[i];
        end
    end
endmodule

verilog-main/drive-download-20260602T032443Z-3-001/EX2/testbench.v
`timescale 1ns / 1ps

module shift_reg_nonblocking_tb;
    reg clk;
    reg D;
    wire [3:0] Q2;

    
    shift_reg_nonblocking u_Q2 (
        .clk(clk),
        .D(D),
        .Q2(Q2)
    );

    
    always #55 clk = ~clk;

    initial 
    begin
        clk = 0;
        D = 0;
        
        
        $dumpfile("shift_reg_nonblocking.vcd");
        $dumpvars(0, shift_reg_nonblocking_tb);

        
        #110 D = 1;
        #110 D = 0;
        #110 D = 1;
        #110 D = 0;
        #110 D = 1;
        #110 D = 0;
        #110 D = 1;
        #110 D = 0;
        #110 D = 1;
        #110 D = 1;
        #110 D = 0;
        #110 D = 1;
        #110 D = 0;
        #110 D = 0;
        #110 D = 1;
        #110 D = 0;
        #110 D = 0;
        #110 D = 1;
        #110 D = 1;
        
        #110;
        $finish; 
    end
endmodule

verilog-main/drive-download-20260602T032443Z-3-001/EX2/shift_reg_nonblocking.vcd
$date
	Tue May 19 11:27:48 2026
$end
$version
	Icarus Verilog
$end
$timescale
	1ps
$end
$scope module shift_reg_nonblocking_tb $end
$var wire 4 ! Q2 [3:0] $end
$var reg 1 " D $end
$var reg 1 # clk $end
$scope module u_Q2 $end
$var wire 1 " D $end
$var wire 1 # clk $end
$var reg 4 $ Q2 [3:0] $end
$var integer 32 % i [31:0] $end
$upscope $end
$upscope $end
$enddefinitions $end
$comment Show the parameter values. $end
$dumpall
$end
#0
$dumpvars
bx %
bx $
0#
0"
bx !
$end
#55000
bx0 !
bx0 $
b11 %
1#
#110000
0#
1"
#165000
bx01 !
bx01 $
b11 %
1#
#220000
0#
0"
#275000
bx010 !
bx010 $
b11 %
1#
#330000
0#
1"
#385000
b101 !
b101 $
b11 %
1#
#440000
0#
0"
#495000
b1010 !
b1010 $
b11 %
1#
#550000
0#
1"
#605000
b101 !
b101 $
b11 %
1#
#660000
0#
0"
#715000
b1010 !
b1010 $
b11 %
1#
#770000
0#
1"
#825000
b101 !
b101 $
b11 %
1#
#880000
0#
0"
#935000
b1010 !
b1010 $
b11 %
1#
#990000
0#
1"
#1045000
b101 !
b101 $
b11 %
1#
#1100000
0#
#1155000
b1011 !
b1011 $
b11 %
1#
#1210000
0#
0"
#1265000
b110 !
b110 $
b11 %
1#
#1320000
0#
1"
#1375000
b1101 !
b1101 $
b11 %
1#
#1430000
0#
0"
#1485000
b1010 !
b1010 $
b11 %
1#
#1540000
0#
#1595000
b100 !
b100 $
b11 %
1#
#1650000
0#
1"
#1705000
b1001 !
b1001 $
b11 %
1#
#1760000
0#
0"
#1815000
b10 !
b10 $
b11 %
1#
#1870000
0#
#1925000
b100 !
b100 $
b11 %
1#
#1980000
0#
1"
#2035000
b1001 !
b1001 $
b11 %
1#
#2090000
0#
#2145000
b11 !
b11 $
b11 %
1#
