20260505_Ex2/design.sv
module ABSY(A, B, S, Y);
  input A, B, S;
  output Y;

  wire notS, notSA, SB;

  not(notS, S);
  and(notSA, notS, A);
  and(SB, S, B);
  or(Y, notSA, SB);

endmodule

20260505_Ex2/testbench.sv
`timescale 1ns/1ns
module ABSY_test();
  // constants
  
  // general purpose registers
  reg A, B, S;
   
  // wires
  wire Yout;

  ABSY uut(
    .A(A),
    .B(B),
    .S(S),
    .Y(Yout)
  );

  initial    
  begin
    A=1'b0; B=1'b0; S=1'b0;
    #20;
    A=1'b0; B=1'b1; S=1'b0;
    #20;
    A=1'b1; B=1'b0; S=1'b0;
    #20;
    A=1'b1; B=1'b1; S=1'b0;
    #20;
    A=1'b0; B=1'b0; S=1'b1;
    #20;
    A=1'b0; B=1'b1; S=1'b1;
    #20;
    A=1'b1; B=1'b0; S=1'b1;
    #20;
    A=1'b1; B=1'b1; S=1'b1;
    #20;
  end 
      
  initial 
  begin
    $display("Starting Testbench...");
    #180;
    $finish();
  end

  initial 
  begin
    $dumpfile("dump.vcd");
    $dumpvars(0);
  end
endmodule

20260505_Ex2/dump.vcd
$date
	Tue Jun  2 10:27:50 2026
$end
$version
	Icarus Verilog
$end
$timescale
	1ns
$end
$scope module ABSY_test $end
$var wire 1 ! Yout $end
$var reg 1 " A $end
$var reg 1 # B $end
$var reg 1 $ S $end
$scope module uut $end
$var wire 1 " A $end
$var wire 1 # B $end
$var wire 1 $ S $end
$var wire 1 % SB $end
$var wire 1 ! Y $end
$var wire 1 & notS $end
$var wire 1 ' notSA $end
$upscope $end
$upscope $end
$enddefinitions $end
$comment Show the parameter values. $end
$dumpall
$end
#0
$dumpvars
0'
1&
0%
0$
0#
0"
0!
$end
#20
1#
#40
1!
1'
0#
1"
#60
1#
#80
0!
0&
0'
1$
0#
0"
#100
1!
1%
1#
#120
0!
0%
0#
1"
#140
1!
1%
1#
