20260526_Ex1/design.sv
module BlockingShiftRegister(Clk, D, Q1);
    input Clk, D;
    output reg [3:0] Q1;
    integer i;

    always @(posedge Clk) begin
        for (i = 3; i > 0; i = i - 1) begin
            Q1[i] = Q1[i - 1];
        end
        Q1[0] = D;
    end
endmodule

module NonBlockingShiftRegister(Clk, D, Q2);
    input Clk, D;
    output reg [3:0] Q2;
    integer i;

    always @(posedge Clk) begin
        for (i = 1; i <= 3; i = i + 1) begin
            Q2[i] <= Q2[i - 1];
        end
        Q2[0] <= D;
    end
endmodule

20260526_Ex1/testbench.sv
`timescale 1ns/1ns

module Practice();
    reg Clk, D;
    wire [3:0] Q1;
    wire [3:0] Q2;

    BlockingShiftRegister q1_inst(
        .Clk(Clk),
        .D(D),
        .Q1(Q1)
    );

    NonBlockingShiftRegister q2_inst(
        .Clk(Clk),
        .D(D),
        .Q2(Q2)
    );

    initial begin
        Clk = 1'b0;
        forever begin
            #100;
            Clk = !Clk;
        end
    end

    initial begin
        D = 1'b0;
        #100;
        D = 1'b1;
        #200;
        D = 1'b0;
        #200;
        D = 1'b1;
        #200;
        D = 1'b0;
        #200;
        D = 1'b1;
        #400;
        D = 1'b0;
        #400;
        D = 1'b1;
        #400;
    end

    initial begin
        $display("Starting Testbench");
        #2200;
        $finish;
    end

    initial begin
        $dumpfile("dump.vcd");
        $dumpvars(0);
    end
endmodule

20260526_Ex1/dump.vcd
$date
	Tue Jun  2 10:27:50 2026
$end
$version
	Icarus Verilog
$end
$timescale
	1ns
$end
$scope module Practice $end
$var wire 4 ! Q2 [3:0] $end
$var wire 4 " Q1 [3:0] $end
$var reg 1 # Clk $end
$var reg 1 $ D $end
$scope module q1_inst $end
$var wire 1 # Clk $end
$var wire 1 $ D $end
$var reg 4 % Q1 [3:0] $end
$var integer 32 & i [31:0] $end
$upscope $end
$scope module q2_inst $end
$var wire 1 # Clk $end
$var wire 1 $ D $end
$var reg 4 ' Q2 [3:0] $end
$var integer 32 ( i [31:0] $end
$upscope $end
$upscope $end
$enddefinitions $end
$comment Show the parameter values. $end
$dumpall
$end
#0
$dumpvars
bx (
bx '
bx &
bx %
0$
0#
bx "
bx !
$end
#100
bx1 !
bx1 '
bx1 "
bx1 %
b0 &
b100 (
1$
1#
#200
0#
#300
bx10 !
bx10 '
b100 (
bx10 "
bx10 %
b0 &
1#
0$
#400
0#
#500
bx101 !
bx101 '
bx101 "
bx101 %
b0 &
b100 (
1#
1$
#600
0#
#700
b1010 !
b1010 '
b100 (
b1010 "
b1010 %
b0 &
1#
0$
#800
0#
#900
b101 !
b101 '
b101 "
b101 %
b0 &
b100 (
1#
1$
#1000
0#
#1100
b1011 !
b1011 '
b100 (
b1011 "
b1011 %
b0 &
1#
#1200
0#
#1300
b110 !
b110 '
b110 "
b110 %
b0 &
b100 (
1#
0$
#1400
0#
#1500
b1100 !
b1100 '
b100 (
b1100 "
b1100 %
b0 &
1#
#1600
0#
#1700
b1001 !
b1001 '
b1001 "
b1001 %
b0 &
b100 (
1#
1$
#1800
0#
#1900
b11 !
b11 '
b100 (
b11 "
b11 %
b0 &
1#
#2000
0#
#2100
b111 !
b111 '
b111 "
b111 %
b0 &
b100 (
1#
